physbo/__init__.py
physbo/predictor.py
physbo/variable.py
physbo/blm/__init__.py
physbo/blm/predictor.py
physbo/blm/basis/__init__.py
physbo/blm/basis/fourier.py
physbo/blm/core/__init__.py
physbo/blm/core/model.py
physbo/blm/inf/__init__.py
physbo/blm/inf/exact.py
physbo/blm/lik/__init__.py
physbo/blm/lik/gauss.py
physbo/blm/lik/linear.py
physbo/blm/lik/_src/__init__.py
physbo/blm/lik/_src/cov.py
physbo/blm/prior/__init__.py
physbo/blm/prior/gauss.py
physbo/gp/__init__.py
physbo/gp/predictor.py
physbo/gp/core/__init__.py
physbo/gp/core/learning.py
physbo/gp/core/model.py
physbo/gp/core/prior.py
physbo/gp/cov/__init__.py
physbo/gp/cov/gauss.py
physbo/gp/cov/_src/__init__.py
physbo/gp/cov/_src/enhance_gauss.cpython-310-darwin.so
physbo/gp/inf/__init__.py
physbo/gp/inf/exact.py
physbo/gp/lik/__init__.py
physbo/gp/lik/gauss.py
physbo/gp/mean/__init__.py
physbo/gp/mean/const.py
physbo/gp/mean/zero.py
physbo/misc/__init__.py
physbo/misc/centering.py
physbo/misc/gauss_elim.py
physbo/misc/set_config.py
physbo/misc/_src/__init__.py
physbo/misc/_src/cholupdate.cpython-310-darwin.so
physbo/misc/_src/diagAB.cpython-310-darwin.so
physbo/misc/_src/logsumexp.cpython-310-darwin.so
physbo/misc/_src/traceAB.cpython-310-darwin.so
physbo/opt/__init__.py
physbo/opt/adam.py
physbo/search/__init__.py
physbo/search/pareto.py
physbo/search/score.py
physbo/search/score_multi.py
physbo/search/utility.py
physbo/search/discrete/__init__.py
physbo/search/discrete/policy.py
physbo/search/discrete/results.py
physbo/search/discrete_multi/__init__.py
physbo/search/discrete_multi/policy.py
physbo/search/discrete_multi/results.py
physbo-2.0.0.dist-info/METADATA
physbo-2.0.0.dist-info/WHEEL
physbo-2.0.0.dist-info/top_level.txt
physbo-2.0.0.dist-info/RECORD
