Metadata-Version: 2.1
Name: physbo
Version: 2.0.0
Summary: optimization tool for PHYSics based on Bayesian Optimization
Home-page: https://github.com/issp-center-dev/PHYSBO
Author: PHYSBO developers
Author-email: physbo-dev@issp.u-tokyo.ac.jp
License: MPLv2
Requires-Python: >=3.6
Requires-Dist: numpy <2.0
Requires-Dist: scipy
